simple_baserow_api/__init__.py
simple_baserow_api/__main__.py
simple_baserow_api/base.py
simple_baserow_api/cli.py
simple_baserow_api-0.1.5.dist-info/licenses/LICENSE
simple_baserow_api-0.1.5.dist-info/METADATA
simple_baserow_api-0.1.5.dist-info/WHEEL
simple_baserow_api-0.1.5.dist-info/entry_points.txt
simple_baserow_api-0.1.5.dist-info/top_level.txt
simple_baserow_api-0.1.5.dist-info/RECORD
