Metadata-Version: 2.4
Name: simple_baserow_api
Version: 0.1.5
Summary: Awesome simple_baserow_api created by KuechlerO
Home-page: https://github.com/KuechlerO/simple_baserow_api/
Author: KuechlerO
License-File: LICENSE
Requires-Dist: requests
Requires-Dist: types-requests
Requires-Dist: pdoc3
Provides-Extra: test
Requires-Dist: pytest; extra == "test"
Requires-Dist: coverage; extra == "test"
Requires-Dist: flake8; extra == "test"
Requires-Dist: black; extra == "test"
Requires-Dist: isort; extra == "test"
Requires-Dist: pytest-cov; extra == "test"
Requires-Dist: mypy; extra == "test"
Requires-Dist: gitchangelog; extra == "test"
Requires-Dist: mkdocs; extra == "test"
Dynamic: author
Dynamic: description
Dynamic: description-content-type
Dynamic: home-page
Dynamic: license-file
Dynamic: provides-extra
Dynamic: requires-dist
Dynamic: summary
